playht/__init__.py
playht/__version__.py
playht/playht.py
playht/tests/__init__.py
playht/tests/test_playht.py
playht-0.0.8.dist-info/METADATA
playht-0.0.8.dist-info/WHEEL
playht-0.0.8.dist-info/top_level.txt
playht-0.0.8.dist-info/RECORD
