Metadata-Version: 2.1
Name: playht
Version: 0.0.8
Summary: Python wrapper for play.ht API
Home-page: https://github.com/rhcproc/playht
Author: Hans Park
Author-email: rhcproc@gmail.com
License: MIT
Classifier: Programming Language :: Python :: 3.6
Classifier: Programming Language :: Python :: 3.7
Classifier: Programming Language :: Python :: 3.8
Classifier: Programming Language :: Python :: 3.9
Classifier: Programming Language :: Python :: 3.10
Classifier: License :: OSI Approved :: MIT License
Classifier: Operating System :: OS Independent
Requires-Python: >=3.5
Requires-Dist: requests
Requires-Dist: tqdm
